odoo8_addon_crm_lead_address_street3-8.0.0.1.0.99.dev17-py3.8-nspkg.pth
odoo_addons/crm_lead_address_street3/README.rst
odoo_addons/crm_lead_address_street3/__init__.py
odoo_addons/crm_lead_address_street3/__openerp__.py
odoo_addons/crm_lead_address_street3/i18n/bg.po
odoo_addons/crm_lead_address_street3/i18n/crm_lead_address_street3.pot
odoo_addons/crm_lead_address_street3/i18n/de.po
odoo_addons/crm_lead_address_street3/i18n/es.po
odoo_addons/crm_lead_address_street3/i18n/fr.po
odoo_addons/crm_lead_address_street3/i18n/hr.po
odoo_addons/crm_lead_address_street3/i18n/it.po
odoo_addons/crm_lead_address_street3/i18n/pt_BR.po
odoo_addons/crm_lead_address_street3/i18n/sk.po
odoo_addons/crm_lead_address_street3/i18n/sl.po
odoo_addons/crm_lead_address_street3/i18n/tr.po
odoo_addons/crm_lead_address_street3/i18n/zh_CN.po
odoo_addons/crm_lead_address_street3/model/__init__.py
odoo_addons/crm_lead_address_street3/model/crm_lead.py
odoo_addons/crm_lead_address_street3/static/description/icon.png
odoo_addons/crm_lead_address_street3/test/test_street3.yml
odoo_addons/crm_lead_address_street3/view/crm_lead_view.xml
odoo8_addon_crm_lead_address_street3-8.0.0.1.0.99.dev17.dist-info/METADATA
odoo8_addon_crm_lead_address_street3-8.0.0.1.0.99.dev17.dist-info/WHEEL
odoo8_addon_crm_lead_address_street3-8.0.0.1.0.99.dev17.dist-info/namespace_packages.txt
odoo8_addon_crm_lead_address_street3-8.0.0.1.0.99.dev17.dist-info/top_level.txt
odoo8_addon_crm_lead_address_street3-8.0.0.1.0.99.dev17.dist-info/RECORD
